MANIFEST.in
README.rst
VERSION
setup.cfg
setup.py
docs/conf.py
docs/index.rst
docs/tutorials/cli.rst
docs/tutorials/python.rst
satbot/__init__.py
satbot/calibration.py
satbot/main.py
satbot/run.py
satbot.egg-info/PKG-INFO
satbot.egg-info/SOURCES.txt
satbot.egg-info/dependency_links.txt
satbot.egg-info/entry_points.txt
satbot.egg-info/top_level.txt
test/test_imports.py