Metadata-Version: 1.1
Name: satbot
Version: 0.1.10
Summary: Read data from commonly-available "satellite" hobby R/C receivers.
Home-page: https://github.com/stnbu/satbot
Author: Mike Burr
Author-email: mburr@unintuitive.org
License: MIT
Download-URL: https://github.com/stnbu/satbot/archive/master.zip
Keywords: r/c,robotics,dsm
Platform: UNKNOWN
Classifier: Development Status :: 4 - Beta
Classifier: License :: OSI Approved :: MIT License
Classifier: Programming Language :: Python :: 2
Classifier: Topic :: Games/Entertainment
Classifier: Topic :: Home Automation
Classifier: Topic :: Software Development :: Embedded Systems
Classifier: Topic :: System :: Hardware
Classifier: Topic :: Terminals :: Serial
Requires: daemon
Requires: pyserial
Provides: satbot
